{
  "collection": "◆ Token/ Semantic Color",
  "collectionId": "VariableCollectionId:139:4134",
  "mode": "Light Theme",
  "value": {
    "token-semantic-color": {
      "frame": {
        "base": {
          "primary": {
            "$type": "color",
            "$value": "{color.neutralGray.light.50}",
            "$extensions": {
              "figma:variables": {
                "variableId": "VariableID:139:4135",
                "modeId": "139:0",
                "resolvedType": "COLOR"
              },
              "resolved-value": "#f2f2f2"
            }
          },
          "secondary": {
            "$type": "color",
            "$value": "{color.neutralGray.light.10}",
            "$extensions": {
              "figma:variables": {
                "variableId": "VariableID:139:4139",
                "modeId": "139:0",
                "resolvedType": "COLOR"
              },
              "resolved-value": "#fcfcfc"
            }
          }
        }
      },
      "background": {
        "base": {
          "primary": {
            "$type": "color",
            "$value": "{color.neutralGray.light.10}",
            "$extensions": {
              "figma:variables": {
                "variableId": "VariableID:139:4140",
                "modeId": "139:0",
                "resolvedType": "COLOR"
              },
              "resolved-value": "#fcfcfc"
            }
          },
          "secondary": {
            "$type": "color",
            "$value": "{color.neutralGray.light.50}",
            "$extensions": {
              "figma:variables": {
                "variableId": "VariableID:139:4141",
                "modeId": "139:0",
                "resolvedType": "COLOR"
              },
              "resolved-value": "#f2f2f2"
            }
          }
        }
      },
      "container": {
        "brand": {
          "primary": {
            "$type": "color",
            "$value": "{color.purple.light.300}",
            "$extensions": {
              "figma:variables": {
                "variableId": "VariableID:139:4142",
                "modeId": "139:0",
                "resolvedType": "COLOR"
              },
              "resolved-value": "#8927fa"
            }
          },
          "secondary": {
            "$type": "color",
            "$value": "{color.neutralGray.light.900}",
            "$extensions": {
              "figma:variables": {
                "variableId": "VariableID:139:4143",
                "modeId": "139:0",
                "resolvedType": "COLOR"
              },
              "resolved-value": "#1a1a1a"
            }
          },
          "primary-low": {
            "$type": "color",
            "$value": "{color.purple.light.10}",
            "$extensions": {
              "figma:variables": {
                "variableId": "VariableID:139:4147",
                "modeId": "139:0",
                "resolvedType": "COLOR"
              },
              "resolved-value": "#f7f0ff"
            }
          },
          "primary-high": {
            "$type": "color",
            "$value": "{color.purple.light.500}",
            "$extensions": {
              "figma:variables": {
                "variableId": "VariableID:139:4148",
                "modeId": "139:0",
                "resolvedType": "COLOR"
              },
              "resolved-value": "#6d1cdf"
            }
          }
        },
        "base": {
          "primary": {
            "$type": "color",
            "$value": "{color.neutralGray.light.10}",
            "$extensions": {
              "figma:variables": {
                "variableId": "VariableID:139:4149",
                "modeId": "139:0",
                "resolvedType": "COLOR"
              },
              "resolved-value": "#fcfcfc"
            }
          },
          "secondary": {
            "$type": "color",
            "$value": "{color.neutralGray.light.50}",
            "$extensions": {
              "figma:variables": {
                "variableId": "VariableID:139:4153",
                "modeId": "139:0",
                "resolvedType": "COLOR"
              },
              "resolved-value": "#f2f2f2"
            }
          },
          "tertiary": {
            "$type": "color",
            "$value": "{color.neutralGray.light.100}",
            "$extensions": {
              "figma:variables": {
                "variableId": "VariableID:139:4157",
                "modeId": "139:0",
                "resolvedType": "COLOR"
              },
              "resolved-value": "#ebebeb"
            }
          },
          "quaternary": {
            "$type": "color",
            "$value": "{color.neutralGray.light.200}",
            "$extensions": {
              "figma:variables": {
                "variableId": "VariableID:139:4160",
                "modeId": "139:0",
                "resolvedType": "COLOR"
              },
              "resolved-value": "#e0e0e0"
            }
          }
        }
      },
      "text": {
        "brand": {
          "primary": {
            "$type": "color",
            "$value": "{color.purple.light.500}",
            "$extensions": {
              "figma:variables": {
                "variableId": "VariableID:139:4169",
                "modeId": "139:0",
                "resolvedType": "COLOR"
              },
              "resolved-value": "#6d1cdf"
            }
          },
          "primary-low": {
            "$type": "color",
            "$value": "{color.purple.light.300}",
            "$extensions": {
              "figma:variables": {
                "variableId": "VariableID:139:4170",
                "modeId": "139:0",
                "resolvedType": "COLOR"
              },
              "resolved-value": "#8927fa"
            }
          },
          "primary-high": {
            "$type": "color",
            "$value": "{color.purple.light.600}",
            "$extensions": {
              "figma:variables": {
                "variableId": "VariableID:139:4175",
                "modeId": "139:0",
                "resolvedType": "COLOR"
              },
              "resolved-value": "#5111c5"
            }
          }
        },
        "base": {
          "primary": {
            "$type": "color",
            "$value": "{color.neutralGray.light.900}",
            "$extensions": {
              "figma:variables": {
                "variableId": "VariableID:139:4171",
                "modeId": "139:0",
                "resolvedType": "COLOR"
              },
              "resolved-value": "#1a1a1a"
            }
          },
          "secondary": {
            "$type": "color",
            "$value": "{color.neutralGray.light.800}",
            "$extensions": {
              "figma:variables": {
                "variableId": "VariableID:139:4172",
                "modeId": "139:0",
                "resolvedType": "COLOR"
              },
              "resolved-value": "#474747"
            }
          },
          "tertiary": {
            "$type": "color",
            "$value": "{color.neutralGray.light.700}",
            "$extensions": {
              "figma:variables": {
                "variableId": "VariableID:139:4173",
                "modeId": "139:0",
                "resolvedType": "COLOR"
              },
              "resolved-value": "#6e6e6e"
            }
          },
          "white": {
            "$type": "color",
            "$value": "{color.bw.white}",
            "$extensions": {
              "figma:variables": {
                "variableId": "VariableID:139:4174",
                "modeId": "139:0",
                "resolvedType": "COLOR"
              },
              "resolved-value": "#ffffff"
            }
          },
          "quaternary": {
            "$type": "color",
            "$value": "{color.neutralGray.light.600}",
            "$extensions": {
              "figma:variables": {
                "variableId": "VariableID:139:4193",
                "modeId": "139:0",
                "resolvedType": "COLOR"
              },
              "resolved-value": "#828282"
            }
          }
        }
      },
      "icon": {
        "brand": {
          "primary-low": {
            "$type": "color",
            "$value": "{color.purple.light.300}",
            "$extensions": {
              "figma:variables": {
                "variableId": "VariableID:139:4177",
                "modeId": "139:0",
                "resolvedType": "COLOR"
              },
              "resolved-value": "#8927fa"
            }
          },
          "primary": {
            "$type": "color",
            "$value": "{color.purple.light.500}",
            "$extensions": {
              "figma:variables": {
                "variableId": "VariableID:139:4178",
                "modeId": "139:0",
                "resolvedType": "COLOR"
              },
              "resolved-value": "#6d1cdf"
            }
          },
          "* secondary (확인필요)": {
            "$type": "color",
            "$value": "{color.neutralGray.light.900}",
            "$extensions": {
              "figma:variables": {
                "variableId": "VariableID:139:4184",
                "modeId": "139:0",
                "resolvedType": "COLOR"
              },
              "resolved-value": "#1a1a1a"
            }
          }
        },
        "base": {
          "primary": {
            "$type": "color",
            "$value": "{color.neutralGray.light.900}",
            "$extensions": {
              "figma:variables": {
                "variableId": "VariableID:139:4179",
                "modeId": "139:0",
                "resolvedType": "COLOR"
              },
              "resolved-value": "#1a1a1a"
            }
          },
          "secondary": {
            "$type": "color",
            "$value": "{color.neutralGray.light.500}",
            "$extensions": {
              "figma:variables": {
                "variableId": "VariableID:139:4180",
                "modeId": "139:0",
                "resolvedType": "COLOR"
              },
              "resolved-value": "#969696"
            }
          },
          "white": {
            "$type": "color",
            "$value": "{color.bw.white}",
            "$extensions": {
              "figma:variables": {
                "variableId": "VariableID:139:4182",
                "modeId": "139:0",
                "resolvedType": "COLOR"
              },
              "resolved-value": "#ffffff"
            }
          }
        }
      },
      "border": {
        "brand": {
          "primary": {
            "$type": "color",
            "$value": "{color.purple.light.500}",
            "$extensions": {
              "figma:variables": {
                "variableId": "VariableID:139:4186",
                "modeId": "139:0",
                "resolvedType": "COLOR"
              },
              "resolved-value": "#6d1cdf"
            }
          },
          "primary-high": {
            "$type": "color",
            "$value": "{color.purple.light.600}",
            "$extensions": {
              "figma:variables": {
                "variableId": "VariableID:139:4191",
                "modeId": "139:0",
                "resolvedType": "COLOR"
              },
              "resolved-value": "#5111c5"
            }
          },
          "secondary": {
            "$type": "color",
            "$value": "{color.neutralGray.light.900}",
            "$extensions": {
              "figma:variables": {
                "variableId": "VariableID:139:4192",
                "modeId": "139:0",
                "resolvedType": "COLOR"
              },
              "resolved-value": "#1a1a1a"
            }
          }
        },
        "base": {
          "primary": {
            "$type": "color",
            "$value": "{color.neutralGray.light.900}",
            "$extensions": {
              "figma:variables": {
                "variableId": "VariableID:139:4187",
                "modeId": "139:0",
                "resolvedType": "COLOR"
              },
              "resolved-value": "#1a1a1a"
            }
          },
          "secondary": {
            "$type": "color",
            "$value": "{color.neutralGray.light.200}",
            "$extensions": {
              "figma:variables": {
                "variableId": "VariableID:139:4188",
                "modeId": "139:0",
                "resolvedType": "COLOR"
              },
              "resolved-value": "#e0e0e0"
            }
          },
          "tertiary": {
            "$type": "color",
            "$value": "{color.neutralGray.light.50}",
            "$extensions": {
              "figma:variables": {
                "variableId": "VariableID:139:4189",
                "modeId": "139:0",
                "resolvedType": "COLOR"
              },
              "resolved-value": "#f2f2f2"
            }
          }
        }
      },
      "status": {
        "container": {
          "disabled": {
            "$type": "color",
            "$value": "{color.neutralGray.light.100}",
            "$extensions": {
              "figma:variables": {
                "variableId": "VariableID:4379:22122",
                "modeId": "139:0",
                "resolvedType": "COLOR"
              },
              "resolved-value": "#ebebeb"
            }
          },
          "* disabled - primary (확인필요)": {
            "$type": "color",
            "$value": "{color.purple.light.100}",
            "$extensions": {
              "figma:variables": {
                "variableId": "VariableID:6548:35488",
                "modeId": "139:0",
                "resolvedType": "COLOR"
              },
              "resolved-value": "#d4bfff"
            }
          }
        },
        "text": {
          "disabled": {
            "$type": "color",
            "$value": "{color.neutralGray.light.400}",
            "$extensions": {
              "figma:variables": {
                "variableId": "VariableID:4379:22180",
                "modeId": "139:0",
                "resolvedType": "COLOR"
              },
              "resolved-value": "#a8a8a8"
            }
          },
          "* disabled - on primary (확인필요)": {
            "$type": "color",
            "$value": "{color.purple.light.10}",
            "$extensions": {
              "figma:variables": {
                "variableId": "VariableID:6548:35530",
                "modeId": "139:0",
                "resolvedType": "COLOR"
              },
              "resolved-value": "#f7f0ff"
            }
          }
        },
        "icon": {
          "disabled": {
            "$type": "color",
            "$value": "{color.neutralGray.light.400}",
            "$extensions": {
              "figma:variables": {
                "variableId": "VariableID:4379:22183",
                "modeId": "139:0",
                "resolvedType": "COLOR"
              },
              "resolved-value": "#a8a8a8"
            }
          },
          "selected": {
            "$type": "color",
            "$value": "{color.neutralGray.light.900}",
            "$extensions": {
              "figma:variables": {
                "variableId": "VariableID:4726:9420",
                "modeId": "139:0",
                "resolvedType": "COLOR"
              },
              "resolved-value": "#1a1a1a"
            }
          },
          "* disabled - on primary (확인필요)": {
            "$type": "color",
            "$value": "{color.purple.light.10}",
            "$extensions": {
              "figma:variables": {
                "variableId": "VariableID:6548:35556",
                "modeId": "139:0",
                "resolvedType": "COLOR"
              },
              "resolved-value": "#f7f0ff"
            }
          }
        },
        "border": {
          "disabled": {
            "$type": "color",
            "$value": "{color.neutralGray.light.100}",
            "$extensions": {
              "figma:variables": {
                "variableId": "VariableID:4379:22273",
                "modeId": "139:0",
                "resolvedType": "COLOR"
              },
              "resolved-value": "#ebebeb"
            }
          }
        }
      },
      "state": {
        "stateLayer": {
          "focused": {
            "$type": "color",
            "$value": "{color.neutralGray.light.900}",
            "$extensions": {
              "figma:variables": {
                "variableId": "VariableID:4663:8185",
                "modeId": "139:0",
                "resolvedType": "COLOR"
              },
              "resolved-value": "#1a1a1a"
            }
          }
        }
      }
    }
  }
}